setup.py
sigmahttp/__init__.py
sigmahttp.egg-info/PKG-INFO
sigmahttp.egg-info/SOURCES.txt
sigmahttp.egg-info/dependency_links.txt
sigmahttp.egg-info/top_level.txt