Metadata-Version: 2.1
Name: sigmahttp
Version: 0.0.1
Summary: SigmaHTTP - modern, async and easy async HTTP framework, written in Python.
Home-page: https://github.com/sigmahttp/sigmahttp
Author: True Sigma
Author-email: sigmahttp@gmail.com
Keywords: http https http-server http_server httpserver http-library http_library httplibrary
Classifier: Development Status :: 1 - Planning
Classifier: Intended Audience :: Developers
Classifier: License :: OSI Approved :: MIT License
Classifier: Programming Language :: Python :: 3
Classifier: Programming Language :: Python :: 3.8
Classifier: Programming Language :: Python :: 3.9
Classifier: Programming Language :: Python :: 3 :: Only
Classifier: Framework :: AsyncIO
Classifier: Topic :: Internet :: WWW/HTTP
Classifier: Topic :: Software Development :: Libraries :: Application Frameworks
